[
  {
    "TripId": "valor-transatlantic-2025",
    "TripName": "Carnival Valor: Transatlantic to Barcelona",
    "IsActiveTravel": true,
    "Segments": [
      {
        "SegmentType": "Cruise",
        "BookingNumber": "CM47Q6",
        "CruiseLine": "Carnival",
        "Ship": "Carnival Valor",
        "RoomType": "Balcony",
        "Stateroom": "8285",
        "DeparturePort": {
          "PortName": "Port of New Orleans",
          "City": "New Orleans",
          "Province": "LA",
          "CountryCode": "US",
          "Time": "2025-04-24T18:00:00-05:00"
        },
        "ArrivalPort": {
          "PortName": "Port of Barcelona",
          "City": "Barcelona",
          "Province": "CT",
          "CountryCode": "ES",
          "Time": "2025-05-10T06:00:00+02:00"
        },
        "PortsOfCall": [
          {
            "PortName": "Nassau",
            "City": "Nassau",
            "Province": null,
            "CountryCode": "BS",
            "Date": "2025-04-27"
          },
          {
            "PortName": "Ponta Delgada",
            "City": "Ponta Delgada",
            "Province": "Azores",
            "CountryCode": "PT",
            "Date": "2025-05-04"
          },
          {
            "PortName": "Funchal",
            "City": "Funchal",
            "Province": "Madeira",
            "CountryCode": "PT",
            "Date": "2025-05-06"
          },
          {
            "PortName": "Malaga",
            "City": "Malaga",
            "Province": "AN",
            "CountryCode": "ES",
            "Date": "2025-05-08"
          },
          {
            "PortName": "Alicante",
            "City": "Alicante",
            "Province": "VC",
            "CountryCode": "ES",
            "Date": "2025-05-09"
          }
        ],
        "Source": "manual"
      }
    ]
  }
]
